shrinkplz/__init__.py
shrinkplz/cli.py
shrinkplz/config.py
shrinkplz/mark.py
shrinkplz/output.py
shrinkplz/state.py
shrinkplz-0.1.2.dist-info/licenses/LICENSE
shrinkplz-0.1.2.dist-info/METADATA
shrinkplz-0.1.2.dist-info/WHEEL
shrinkplz-0.1.2.dist-info/entry_points.txt
shrinkplz-0.1.2.dist-info/top_level.txt
shrinkplz-0.1.2.dist-info/RECORD
