Metadata-Version: 2.4
Name: shrinkplz
Version: 0.1.2
Summary: A command line tool to help you shrink failing test data
License-Expression: MIT
Project-URL: Homepage, https://github.com/rtpg/shrinkplz
Project-URL: Repository, https://github.com/rtpg/shrinkplz.git
Project-URL: Issues, https://github.com/rtpg/shrinkplz/issues
Classifier: Development Status :: 4 - Beta
Classifier: Topic :: Software Development :: Testing
Requires-Python: >=3.12
License-File: LICENSE
Requires-Dist: pytest>=8.4.1
Dynamic: license-file
